artifacts/__init__.py
artifacts/__main__.py
artifacts/authorization.py
artifacts/awsutils/__init__.py
artifacts/awsutils/dynamodb.py
artifacts/pipeline.py
artifacts/topology.py
artifacts/utils.py
tcloud_codeartifact_test-0.1.0.dist-info/WHEEL
tcloud_codeartifact_test-0.1.0.dist-info/METADATA
tcloud_codeartifact_test-0.1.0.dist-info/RECORD
