Metadata-Version: 2.1
Name: tcloud-codeartifact-test
Version: 0.1.0
Summary: Code artifact of tcloud
Author: pyaoponto
Author-email: pyaoponto@gmail.com
Requires-Python: >=3.8
Classifier: Programming Language :: Python :: 3
Classifier: Programming Language :: Python :: 3.8
Classifier: Programming Language :: Python :: 3.9
Classifier: Programming Language :: Python :: 3.10
Requires-Dist: Faker (==8.4.0)
